{
    "swagger": "2.0",
    "info": {
        "description": "NASA daily imaging service",
        "title": "APOD Service",
        "contact": {}
    },
    "paths": {
        "/album/": {
            "post": {
                "description": "create new albums",
                "consumes": [
                    "application/json"
                ],
                "produces": [
                    "application/json"
                ],
                "tags": [
                    "images"
                ],
                "summary": "createPerm",
                "parameters": [
                    {
                        "description": "NASA",
                        "name": "input",
                        "in": "body",
                        "required": true,
                        "schema": {
                            "$ref": "#/definitions/model.Nasa"
                        }
                    }
                ],
                "responses": {
                    "201": {
                        "description": "Created",
                        "schema": {
                            "type": "object",
                            "additionalProperties": {
                                "type": "integer"
                            }
                        }
                    },
                    "400": {
                        "description": "Bad Request",
                        "schema": {
                            "$ref": "#/definitions/model.ErrorResponse"
                        }
                    },
                    "500": {
                        "description": "Internal Server Error",
                        "schema": {
                            "$ref": "#/definitions/model.ErrorResponse"
                        }
                    }
                }
            }
        },
        "/album/dt": {
            "get": {
                "description": "gets image by date",
                "consumes": [
                    "application/json"
                ],
                "produces": [
                    "application/json"
                ],
                "tags": [
                    "images"
                ],
                "summary": "getByDate",
                "responses": {
                    "200": {
                        "description": "OK",
                        "schema": {
                            "$ref": "#/definitions/model.Nasa"
                        }
                    },
                    "500": {
                        "description": "Internal Server Error",
                        "schema": {
                            "$ref": "#/definitions/model.ErrorResponse"
                        }
                    }
                }
            }
        },
        "/album/filter": {
            "get": {
                "description": "gets all images with filter",
                "consumes": [
                    "application/json"
                ],
                "produces": [
                    "application/json"
                ],
                "tags": [
                    "images"
                ],
                "summary": "getWithFilter",
                "parameters": [
                    {
                        "description": "Filter",
                        "name": "input",
                        "in": "body",
                        "required": true,
                        "schema": {
                            "$ref": "#/definitions/model.ApodQueryInput"
                        }
                    }
                ],
                "responses": {
                    "200": {
                        "description": "OK",
                        "schema": {
                            "$ref": "#/definitions/model.ListNasa"
                        }
                    },
                    "500": {
                        "description": "Internal Server Error",
                        "schema": {
                            "$ref": "#/definitions/model.ErrorResponse"
                        }
                    }
                }
            }
        },
        "/album/images": {
            "get": {
                "description": "gets all images from DB",
                "consumes": [
                    "application/json"
                ],
                "produces": [
                    "application/json"
                ],
                "tags": [
                    "images"
                ],
                "summary": "getImagesFromDB",
                "responses": {
                    "200": {
                        "description": "OK",
                        "schema": {
                            "$ref": "#/definitions/model.ListNasa"
                        }
                    },
                    "500": {
                        "description": "Internal Server Error",
                        "schema": {
                            "$ref": "#/definitions/model.ErrorResponse"
                        }
                    }
                }
            }
        }
    },
    "definitions": {
        "model.ApodQueryInput": {
            "type": "object",
            "properties": {
                "count": {
                    "type": "integer"
                },
                "date": {
                    "type": "string"
                },
                "end_date": {
                    "type": "string"
                },
                "start_date": {
                    "type": "string"
                },
                "thumbs": {
                    "type": "boolean"
                }
            }
        },
        "model.ErrorResponse": {
            "type": "object",
            "properties": {
                "message": {
                    "type": "string"
                }
            }
        },
        "model.ListNasa": {
            "type": "object",
            "properties": {
                "data": {
                    "type": "array",
                    "items": {
                        "$ref": "#/definitions/model.Nasa"
                    }
                }
            }
        },
        "model.Nasa": {
            "type": "object",
            "properties": {
                "copyright": {
                    "type": "string"
                },
                "date": {
                    "type": "string"
                },
                "explanation": {
                    "type": "string"
                },
                "hdurl": {
                    "type": "string"
                },
                "id": {
                    "type": "integer"
                },
                "media_type": {
                    "type": "string"
                },
                "service_version": {
                    "type": "string"
                },
                "title": {
                    "type": "string"
                },
                "url": {
                    "type": "string"
                }
            }
        }
    }
}